aui2/__init__.py
aui2/aui_constants.py
aui2/aui_switcherdialog.py
aui2/aui_utilities.py
aui2/auibar.py
aui2/auibook.py
aui2/dockart.py
aui2/framemanager.py
aui2/tabart.py
aui2/tabmdi.py
aui2/version.py
aui2-0.2.0.dist-info/METADATA
aui2-0.2.0.dist-info/WHEEL
aui2-0.2.0.dist-info/top_level.txt
aui2-0.2.0.dist-info/RECORD
