Metadata-Version: 2.4
Name: aui2
Version: 0.2.0
Summary: wxPython Advanced User Interface library 2
Author-email: Tianzhu Qiao <tq@feiyilin.com>
Project-URL: Homepage, https://github.com/tianzhuqiao/aui
Classifier: Operating System :: OS Independent
Requires-Python: >=3.0
Requires-Dist: wxpython>=4.2.1
